{
  "project_info": {
    "project_number": "317214982580",
    "project_id": "plantdisease-e827d",
    "storage_bucket": "plantdisease-e827d.firebasestorage.app"
  },
  "client": [
    {
      "client_info": {
        "mobilesdk_app_id": "1:317214982580:android:b5cdc69e7eca00ab1172e1",
        "android_client_info": {
          "package_name": "com.example.farm_tech"
        }
      },
      "oauth_client": [],
      "api_key": [
        {
          "current_key": "AIzaSyBNimQqfcuqd7qTnRIU_GCN12HlnaT9F5c"
        }
      ],
      "services": {
        "appinvite_service": {
          "other_platform_oauth_client": []
        }
      }
    }
  ],
  "configuration_version": "1"
}